tests/__init__.py
tests/test_sign.py
tieba/__init__.py
tieba/sign.py
tieba_sign-0.8.0.dist-info/METADATA
tieba_sign-0.8.0.dist-info/WHEEL
tieba_sign-0.8.0.dist-info/entry_points.txt
tieba_sign-0.8.0.dist-info/top_level.txt
tieba_sign-0.8.0.dist-info/RECORD
