Metadata-Version: 2.1
Name: tieba-sign
Version: 0.8.0
Summary: 贴吧自动签到
Home-page: https://github.com/zcq100/tieba-sign
Author: zcq100
Author-email: zcq100@gmail.com
License: MIT
Classifier: Programming Language :: Python :: 3
Classifier: License :: OSI Approved :: MIT License
Classifier: Operating System :: OS Independent
Classifier: Topic :: Utilities
Classifier: Topic :: Internet
Requires-Python: >=3.6
Requires-Dist: requests
